sqlitedao/__init__.py
sqlitedao/sanitize.py
sqlitedao/sqlitedao.py
sqlitedao-0.8.0.dist-info/METADATA
sqlitedao-0.8.0.dist-info/WHEEL
sqlitedao-0.8.0.dist-info/top_level.txt
sqlitedao-0.8.0.dist-info/RECORD
