Metadata-Version: 2.2
Name: sqlitedao
Version: 0.8.0
Summary: simple DAO builder and abstraction for sqlite
Home-page: https://github.com/Aperocky/sqlitedao
Author: Rocky Li
Author-email: aperocky@gmail.com
License: MIT
Dynamic: author
Dynamic: author-email
Dynamic: description
Dynamic: description-content-type
Dynamic: home-page
Dynamic: license
Dynamic: summary
